portico/__init__.py
portico/base.py
portico/fn.py
portico/s3.py
portico/sns.py
portico-0.1.0.dist-info/DESCRIPTION.rst
portico-0.1.0.dist-info/METADATA
portico-0.1.0.dist-info/metadata.json
portico-0.1.0.dist-info/RECORD
portico-0.1.0.dist-info/top_level.txt
portico-0.1.0.dist-info/WHEEL
