Metadata-Version: 2.0
Name: portico
Version: 0.1.0
Summary: decorator library for aws lambda functions
Home-page: https://github.com/binarydud/portico
Author: Matt George
Author-email: mgeorge@gmail.com
License: MIT
Platform: UNKNOWN
Requires-Dist: structlog (==16.1.0)
